event_outbox/__init__.py
event_outbox/outbox.py
event_outbox/py.typed
event_outbox-0.4.0.dist-info/METADATA
event_outbox-0.4.0.dist-info/WHEEL
event_outbox-0.4.0.dist-info/RECORD
